examples
ksrpdfparser
tests
venv
