Metadata-Version: 2.4
Name: ksrpdfparser
Version: 0.1.1
Summary: A library for extracting text, images, tables, and layout information from PDF files.
Author: Siva Reddy Kanala
Author-email: Siva Reddy Kanala <ksivareddy1997@gmail.com>
License: MIT
Requires-Python: >=3.7
Requires-Dist: pymupdf>=1.22.0
Requires-Dist: pdfplumber>=0.9.0
Dynamic: author
Dynamic: requires-python
